{
  "submitter"                         : "HelmholtzAI",
  "division"                          : "closed",
  "status"                            : "onprem",
  "system_name"                       : "juwelsbooster_gpu_n64_pytorch1.13",
  "number_of_nodes"                   : "640",
  "host_processors_per_node"          : "2",
  "host_processor_model_name"         : "AMD EPYC 7402",
  "host_processor_core_count"         : "24",
  "host_processor_vcpu_count"         : "",
  "host_processor_frequency"          : "",
  "host_processor_caches"             : "",
  "host_processor_interconnect"       : "",
  "host_memory_capacity"              : "512 GB",
  "host_storage_type"                 : "",
  "host_storage_capacity"             : "",
  "host_networking"                   : "4x Mellanox HDR200 InfiniBand ConnectX 6",
  "host_networking_topology"          : "Dragonfly network topology",
  "host_memory_configuration"         : "",
  "accelerators_per_node"             : "4",
  "accelerator_model_name"            : "NVIDIA A100-PCIE-40GB",
  "accelerator_host_interconnect"     : "PCIe 4 x16",
  "accelerator_frequency"             : "1410 MHz",
  "accelerator_on-chip_memories"      : "",
  "accelerator_memory_configuration"  : "",
  "accelerator_memory_capacity"       : "40 GB",
  "accelerator_interconnect"          : "",
  "accelerator_interconnect_topology" : "",
  "cooling"                           : "",
  "hw_notes"                          : "",
  "framework"                         : "PyTorch 1.13.0a+d321be6",
  "other_software_stack"              : {
      "Singulartiy": "3.8.7-1.el8",
      "Container" : "nvcr.io/nvidia/pytorch:22.08-py3",
      "OpenMPI": "4.1.2rc4+",
      "Python": "3.8.13",
      "NCCL": "2.12.12",
      "cuDNN": "8.5.0.96",
      "CUDA": "11.7.1",
      "cuBLAS": "11.10.3.66"
    },
  "operating_system"                  : "CentOS 8",
  "sw_notes"                          : ""
}
